<?xml version="1.0" encoding="UTF-8"?>
<objects serializationModel="Studio.02.00.00">
	<object class="AudioFile" id="{2d1aa92f-5327-46e0-ad04-1f88311e62a9}">
		<property name="assetPath">
			<value>finish.wav</value>
		</property>
		<property name="frequencyInKHz">
			<value>44.0999985</value>
		</property>
		<property name="channelCount">
			<value>2</value>
		</property>
		<property name="length">
			<value>4.0066893424036278</value>
		</property>
		<relationship name="masterAssetFolder">
			<destination>{8adead9d-e77b-41e4-b031-1e051b3c97c3}</destination>
		</relationship>
	</object>
</objects>
